leftdefault.py
leftdefault-2023.4.15.dist-info/LICENSE.txt
leftdefault-2023.4.15.dist-info/WHEEL
leftdefault-2023.4.15.dist-info/METADATA
leftdefault-2023.4.15.dist-info/RECORD
