Metadata-Version: 2.1
Name: leftdefault
Version: 2023.4.15
Summary: Support for default arguments on the left
Author-email: Nicolas Tessore <n.tessore@ucl.ac.uk>, Nathaniel Starkman <n.starkman@mail.utoronto.ca>
Requires-Python: >=3.8
Classifier: License :: OSI Approved :: MIT License
Project-URL: Home, https://github.com/ntessore/leftdefault
Project-URL: Issues, https://github.com/ntessore/leftdefault/issues
